README.md
setup.py
adapter/__init__.py
adapter/dbadapter.py
adapter/models/__init__.py
adapter/models/base.py
adapter/models/tags.py
adapter_normalizer.egg-info/PKG-INFO
adapter_normalizer.egg-info/SOURCES.txt
adapter_normalizer.egg-info/dependency_links.txt
adapter_normalizer.egg-info/requires.txt
adapter_normalizer.egg-info/top_level.txt