Metadata-Version: 2.1
Name: adapter-normalizer
Version: 0.1.3
Summary: adapter for db
Author: Lev Belous
Author-email: leva22.08.01@inbox.ru
Requires-Python: >=3.9
Requires-Dist: sqlalchemy
Requires-Dist: asyncpg
Requires-Dist: greenlet
